setup.cfg
setup.py
safarisync/__init__.py
safarisync/safarisync.py
safarisync.egg-info/PKG-INFO
safarisync.egg-info/SOURCES.txt
safarisync.egg-info/dependency_links.txt
safarisync.egg-info/entry_points.txt
safarisync.egg-info/requires.txt
safarisync.egg-info/top_level.txt
safarisync.egg-info/zip-safe
