Metadata-Version: 1.0
Name: safarisync
Version: 1.0
Summary: Tool for web scraping and syncing safari downloads library.
Home-page: http://douglas.mayle.org
Author: Douglas Mayle
Author-email: UNKNOWN
License: MIT
Keywords: lxml scraping
Platform: UNKNOWN
